memory_fs/Memory_FS.py
memory_fs/__init__.py
memory_fs/file_fs/File_FS.py
memory_fs/file_fs/README.md
memory_fs/file_fs/__init__.py
memory_fs/file_fs/actions/File_FS__Create.py
memory_fs/file_fs/actions/File_FS__Delete.py
memory_fs/file_fs/actions/File_FS__Exists.py
memory_fs/file_fs/actions/File_FS__Info.py
memory_fs/file_fs/actions/File_FS__Name.py
memory_fs/file_fs/actions/File_FS__Paths.py
memory_fs/file_fs/actions/File_FS__Serializer.py
memory_fs/file_fs/actions/File_FS__Update.py
memory_fs/file_fs/actions/__init__.py
memory_fs/file_fs/file/File_FS__Config.py
memory_fs/file_fs/file/File_FS__Content.py
memory_fs/file_fs/file/File_FS__File.py
memory_fs/file_fs/file/File_FS__Metadata.py
memory_fs/file_fs/file/__init__.py
memory_fs/file_types/Memory_FS__File__Type__Binary.py
memory_fs/file_types/Memory_FS__File__Type__Data.py
memory_fs/file_types/Memory_FS__File__Type__Html.py
memory_fs/file_types/Memory_FS__File__Type__Jpeg.py
memory_fs/file_types/Memory_FS__File__Type__Json.py
memory_fs/file_types/Memory_FS__File__Type__Json__Single.py
memory_fs/file_types/Memory_FS__File__Type__Markdown.py
memory_fs/file_types/Memory_FS__File__Type__Png.py
memory_fs/file_types/Memory_FS__File__Type__Text.py
memory_fs/file_types/__init__.py
memory_fs/helpers/Memory_FS__In_Memory.py
memory_fs/helpers/Memory_FS__Latest.py
memory_fs/helpers/Memory_FS__Latest_Temporal.py
memory_fs/helpers/Memory_FS__Temporal.py
memory_fs/helpers/Memory_FS__Versioned.py
memory_fs/helpers/Memory_FS__Versioned_Latest.py
memory_fs/helpers/__init__.py
memory_fs/path_handlers/Path__Handler.py
memory_fs/path_handlers/Path__Handler__Custom.py
memory_fs/path_handlers/Path__Handler__Hash_Sharded.py
memory_fs/path_handlers/Path__Handler__Key_Based.py
memory_fs/path_handlers/Path__Handler__Latest.py
memory_fs/path_handlers/Path__Handler__Temporal.py
memory_fs/path_handlers/Path__Handler__Versioned.py
memory_fs/path_handlers/__init__.py
memory_fs/schemas/Enum__Memory_FS__File__Content_Type.py
memory_fs-0.41.0.dist-info/LICENSE
memory_fs-0.41.0.dist-info/METADATA
memory_fs-0.41.0.dist-info/WHEEL
memory_fs-0.41.0.dist-info/RECORD
