Metadata-Version: 2.1
Name: memory_fs
Version: 0.41.0
Summary: Memory-FS
Home-page: https://github.com/owasp-sbot/Memory-FS
License: Apache 2.0
Author: Dinis Cruz
Author-email: dinis.cruz@owasp.org
Requires-Python: >=3.12,<4.0
Classifier: License :: Other/Proprietary License
Classifier: Programming Language :: Python :: 3
Classifier: Programming Language :: Python :: 3.12
Requires-Dist: osbot-utils
Project-URL: Repository, https://github.com/owasp-sbot/Memory-FS
